xcsoar.so
xcsoar-0.6.2.dist-info/METADATA
xcsoar-0.6.2.dist-info/WHEEL
xcsoar-0.6.2.dist-info/top_level.txt
xcsoar-0.6.2.dist-info/RECORD
