Metadata-Version: 2.1
Name: xcsoar
Version: 0.6.2
Summary: XCSoar flight analysis tools
Home-page: http://www.xcsoar.org/
Maintainer: Tobias Bieniek
Maintainer-email: tobias.bieniek@gmx.de
License: GPLv2
Platform: UNKNOWN
Classifier: Development Status :: 3 - Alpha
Classifier: Intended Audience :: Developers
Classifier: Intended Audience :: Science/Research
Classifier: License :: OSI Approved :: GNU General Public License v2 (GPLv2)
Classifier: Operating System :: Unix
Classifier: Programming Language :: C++
Classifier: Topic :: Scientific/Engineering :: Information Analysis
